xshap/__init__.py
xshap/xshap.py
xshap-0.1.1.dist-info/LICENSE.txt
xshap-0.1.1.dist-info/METADATA
xshap-0.1.1.dist-info/WHEEL
xshap-0.1.1.dist-info/top_level.txt
xshap-0.1.1.dist-info/RECORD
